README.rst
setup.py
plotserver/__init__.py
plotserver.egg-info/PKG-INFO
plotserver.egg-info/SOURCES.txt
plotserver.egg-info/dependency_links.txt
plotserver.egg-info/requires.txt
plotserver.egg-info/top_level.txt