Metadata-Version: 1.0
Name: plotserver
Version: 0.5
Summary: Expose matplotlib figures over http
Home-page: https://github.com/huyng/plotserver
Author: Huy Nguyen
Author-email: huy@huyng.com
License: UNKNOWN
Platform: UNKNOWN
